bdnotice/__init__.py
bdnotice/notices-template.html
bdnotice-0.1.0.dist-info/entry_points.txt
bdnotice-0.1.0.dist-info/WHEEL
bdnotice-0.1.0.dist-info/METADATA
bdnotice-0.1.0.dist-info/RECORD
