Metadata-Version: 2.1
Name: bdnotice
Version: 0.1.0
Summary: Generate Notice file from Blackduck in JSON, TEXT or HTML format
License: MIT
Author: dineshr93gmail.com
Requires-Python: >=3.8,<4.0
Classifier: License :: OSI Approved :: MIT License
Classifier: Programming Language :: Python :: 3
Classifier: Programming Language :: Python :: 3.10
Classifier: Programming Language :: Python :: 3.8
Classifier: Programming Language :: Python :: 3.9
